hop3_testing/__init__.py
hop3_testing/apps/__init__.py
hop3_testing/apps/catalog.py
hop3_testing/apps/debug.py
hop3_testing/apps/deployment.py
hop3_testing/apps/preparation.py
hop3_testing/apps/verification.py
hop3_testing/catalog/__init__.py
hop3_testing/catalog/loader.py
hop3_testing/catalog/models.py
hop3_testing/catalog/scanner.py
hop3_testing/cli/__init__.py
hop3_testing/cli/commands/__init__.py
hop3_testing/cli/commands/build.py
hop3_testing/cli/commands/catalog.py
hop3_testing/cli/commands/modes.py
hop3_testing/cli/commands/run.py
hop3_testing/cli/commands/test.py
hop3_testing/cli/helpers.py
hop3_testing/cli/reports.py
hop3_testing/cli/runners.py
hop3_testing/diagnostics.py
hop3_testing/results/__init__.py
hop3_testing/results/models.py
hop3_testing/results/reporters.py
hop3_testing/results/store.py
hop3_testing/runners/__init__.py
hop3_testing/runners/base.py
hop3_testing/runners/demo.py
hop3_testing/runners/deployment.py
hop3_testing/runners/tutorial.py
hop3_testing/runners/validations.py
hop3_testing/selector/__init__.py
hop3_testing/selector/modes.py
hop3_testing/selector/selector.py
hop3_testing/targets/__init__.py
hop3_testing/targets/base.py
hop3_testing/targets/config.py
hop3_testing/targets/constants.py
hop3_testing/targets/docker.py
hop3_testing/targets/helpers.py
hop3_testing/targets/remote.py
hop3_testing/util/__init__.py
hop3_testing/util/console.py
hop3_testing-0.4.0b1.dist-info/WHEEL
hop3_testing-0.4.0b1.dist-info/entry_points.txt
hop3_testing-0.4.0b1.dist-info/METADATA
hop3_testing-0.4.0b1.dist-info/RECORD
