Metadata-Version: 2.3
Name: hop3-testing
Version: 0.4.0b1
Summary: Testing utilities for Hop3
Author: Stefane Fermigier
Author-email: Stefane Fermigier <sf@abilian.com>
Requires-Dist: hop3-cli
Requires-Dist: pytest>=8.0.0
Requires-Dist: docker>=7.0.0
Requires-Dist: tomli>=2.0.0 ; python_full_version < '3.11'
Requires-Dist: devtools>=0.12.2
Requires-Dist: python-dotenv>=1.0.1
Requires-Dist: httpcore>=1.0.6
Requires-Dist: httpx>=0.27.2
Requires-Dist: paramiko>=2.11.0,<3.0.0
Requires-Dist: click>=8.0.0
Requires-Dist: sqlalchemy>=2.0.0
Requires-Python: >=3.10, <4
